LICENSE
MANIFEST.in
README.md
setup.py
containershare/__init__.py
containershare/container.py
containershare/defaults.py
containershare/utils.py
containershare/version.py
containershare.egg-info/PKG-INFO
containershare.egg-info/SOURCES.txt
containershare.egg-info/dependency_links.txt
containershare.egg-info/entry_points.txt
containershare.egg-info/not-zip-safe
containershare.egg-info/requires.txt
containershare.egg-info/top_level.txt
containershare/__pycache__/__init__.cpython-36.pyc
containershare/__pycache__/container.cpython-36.pyc
containershare/__pycache__/defaults.cpython-36.pyc
containershare/__pycache__/utils.cpython-36.pyc
containershare/logger/__init__.py
containershare/logger/message.py
containershare/logger/progress.py
containershare/logger/spinner.py
containershare/logger/__pycache__/__init__.cpython-36.pyc
containershare/logger/__pycache__/message.cpython-36.pyc
containershare/logger/__pycache__/progress.cpython-36.pyc
containershare/logger/__pycache__/spinner.cpython-36.pyc
containershare/validator/__init__.py
containershare/validator/library.py
containershare/validator/runtime.py
containershare/validator/utils.py
containershare/validator/__pycache__/__init__.cpython-36.pyc
containershare/validator/__pycache__/library.cpython-36.pyc
containershare/validator/__pycache__/utils.cpython-36.pyc