Metadata-Version: 1.1
Name: containershare
Version: 0.0.12
Summary: library for working with containers, eventually will be goLang
Home-page: http://www.github.com/vsoch/containershare-python
Author: Vanessa Sochat
Author-email: vsochat@stanford.edu
License: LICENSE
Keywords: containers,share,reproducibility,reproducible science
Platform: UNKNOWN
Classifier: Intended Audience :: Science/Research
Classifier: Intended Audience :: Developers
Classifier: License :: OSI Approved :: MIT License
Classifier: Programming Language :: C
Classifier: Programming Language :: Python
Classifier: Topic :: Software Development
Classifier: Topic :: Scientific/Engineering
Classifier: Operating System :: Unix
Classifier: Programming Language :: Python :: 2.7
Classifier: Programming Language :: Python :: 3
